cython_bbox.cp38-win_amd64.pyd
cython_bbox_windows.cp38-win_amd64.pyd
cython_bbox_windows-0.1.3.dist-info/METADATA
cython_bbox_windows-0.1.3.dist-info/WHEEL
cython_bbox_windows-0.1.3.dist-info/top_level.txt
cython_bbox_windows-0.1.3.dist-info/RECORD
