Metadata-Version: 2.1
Name: cython-bbox-windows
Version: 0.1.3
Summary: Standalone cython_bbox_windows
Home-page: https://github.com/samson-wang/cython_bbox.git
Author: Samson Wang
Author-email: samson.c.wang@gmail.com
License: UNKNOWN
Keywords: cython_bbox_windows
Platform: UNKNOWN
